[
  {
    "id": "vehicle",
    "name": "载具",
    "deprecated": false,
    "attributes": [
      {
        "id": "vehicle_yard_id",
        "type": "s",
        "name": "集结点id"
      },
      {
        "id": "task_id",
        "type": "s",
        "name": "任务id"
      },
      {
        "id": "vehicle_name",
        "type": "s",
        "name": "载具名称"
      },
      {
        "id": "length",
        "type": "n",
        "name": "长"
      },
      {
        "id": "width",
        "type": "n",
        "name": "宽"
      },
      {
        "id": "height",
        "type": "n",
        "name": "高"
      },
      {
        "id": "empty_weight",
        "type": "n",
        "name": "空载重量"
      },
      {
        "id": "max_takeoff_weight",
        "type": "n",
        "name": "最大起飞重量"
      },
      {
        "id": "max_people_count",
        "type": "n",
        "name": "最大运输人数"
      },
      {
        "id": "rotor_diameter",
        "type": "n",
        "name": "旋翼直径"
      },
      {
        "id": "tail_rotor_diameter",
        "type": "n",
        "name": "尾桨直径"
      },
      {
        "id": "rated_flow",
        "type": "n",
        "name": "额定排水流量"
      },
      {
        "id": "rated_head",
        "type": "n",
        "name": "额定扬程"
      },
      {
        "id": "pumping_need_min_depth",
        "type": "n",
        "name": "抽水所需最低水深"
      }
    ],
    "bundles": [
      "mobile",
      "transform",
      "controlled",
      "container",
      "vehicle"
    ]
  },
  {
    "id": "slope",
    "name": "边坡",
    "deprecated": false,
    "attributes": [
      {
        "id": "transform/position"
      },
      {
        "id": "slope_name",
        "type": "s",
        "name": "名称"
      },
      {
        "id": "slope_type",
        "type": "s",
        "name": "区分左右"
      },
      {
        "id": "slope_height",
        "type": "n",
        "name": "边坡高度"
      }
    ],
    "bundles": [
      "transform"
    ]
  },
  {
    "id": "debris_flow",
    "name": "泥石流",
    "deprecated": false,
    "attributes": [
      {
        "id": "transform/position"
      },
      {
        "id": "region",
        "type": "n[]",
        "name": "泥石流区域"
      },
      {
        "id": "area",
        "type": "n[]",
        "name": "泥石流面积"
      },
      {
        "id": "volume",
        "type": "n",
        "name": "泥石流量"
      },
      {
        "id": "state",
        "type": "s",
        "name": "泥石流状态"
      },
      {
        "id": "type",
        "type": "s",
        "name": "流域形态"
      },
      {
        "id": "form",
        "type": "s",
        "name": "物质状态"
      }
    ]
  },
  {
    "id": "landslide",
    "name": "滑坡体",
    "deprecated": false,
    "attributes": [
      {
        "id": "transform/position"
      },
      {
        "id": "landslide_amount",
        "type": "n",
        "name": "滑坡量"
      },
      {
        "id": "excavated_volume",
        "type": "n",
        "name": "已挖方量"
      },
      {
        "id": "landslide_height",
        "type": "n",
        "name": "滑坡体高度"
      },
      {
        "id": "landslide_up_width",
        "type": "n",
        "name": "滑坡体上宽"
      },
      {
        "id": "landslide_down_width",
        "type": "n",
        "name": "滑坡体底宽"
      },
      {
        "id": "landslide_incline length",
        "type": "n",
        "name": "滑坡体斜面长"
      },
      {
        "id": "digger_arr",
        "type": "n[]",
        "name": "挖掘机工作点"
      }
    ],
    "bundles": [
      "transform"
    ]
  },
  {
    "id": "dock",
    "name": "码头",
    "deprecated": false,
    "attributes": [
      {
        "id": "dike",
        "type": "s",
        "name": "所在堤坝"
      },
      {
        "id": "transform/position"
      }
    ]
  },
  {
    "id": "drain_device",
    "name": "排水设备",
    "deprecated": false,
    "attributes": [
      {
        "id": "task_id",
        "type": "s",
        "name": "任务id"
      },
      {
        "id": "type",
        "type": "s",
        "name": "设备类型"
      },
      {
        "id": "rated_flow",
        "type": "n",
        "name": "额定排水流量"
      },
      {
        "id": "rated_head",
        "type": "n",
        "name": "额定扬程"
      },
      {
        "id": "pumping_need_min_depth",
        "type": "n",
        "name": "抽水所需最低水深"
      },
      {
        "id": "width",
        "type": "n",
        "name": "宽度"
      },
      {
        "id": "height",
        "type": "n",
        "name": "高度"
      },
      {
        "id": "length",
        "type": "n",
        "name": "长度"
      }
    ]
  },
  {
    "id": "instance_factory",
    "name": "实例工厂",
    "deprecated": false,
    "attributes": [
      {
        "id": "$instances",
        "type": "u"
      }
    ]
  },
  {
    "id": "terrain",
    "name": "地形",
    "deprecated": false,
    "bundles": [
      "terrain"
    ]
  },
  {
    "id": "material_yard",
    "name": "物料场所",
    "deprecated": false,
    "attributes": [
      {
        "id": "transform/position"
      }
    ],
    "bundles": [
      "container"
    ]
  },
  {
    "id": "scene",
    "name": "场景",
    "deprecated": false,
    "attributes": [
      {
        "id": "scene_id",
        "type": "s",
        "name": "场景ID"
      },
      {
        "id": "scene_type",
        "type": "s",
        "name": "场景类型"
      },
      {
        "id": "scene_area",
        "type": "n",
        "name": "场景面积"
      },
      {
        "id": "scene_category",
        "type": "s",
        "name": "场景分类"
      },
      {
        "id": "model_config",
        "type": "s",
        "name": "模型设置"
      },
      {
        "id": "region",
        "type": "n[][]",
        "name": "场景区域"
      },
      {
        "id": "four_points",
        "type": "n[][]",
        "name": "四至点集合"
      },
      {
        "id": "dem_file_name",
        "type": "s",
        "name": "dem文件名"
      },
      {
        "id": "upstream_depth",
        "type": "n",
        "name": "上游水深"
      },
      {
        "id": "material_transportation_distance",
        "type": "n",
        "name": "物料运输距离"
      },
      {
        "id": "scene_date",
        "type": "s",
        "name": "场景开始推演时间"
      },
      {
        "id": "suggestions_data",
        "type": "u",
        "name": "场景资源建议数据"
      },
      {
        "id": "suggestions_scheme_config",
        "type": "u",
        "name": "推荐方案设置"
      }
    ],
    "bundles": [
      "transform"
    ]
  },
  {
    "id": "plan",
    "name": "救援方案",
    "deprecated": false,
    "attributes": [
      {
        "id": "controlled/status"
      },
      {
        "id": "tasks",
        "type": "u[]",
        "name": "任务集合"
      },
      {
        "id": "amount",
        "type": "n",
        "name": "方案总计任务量"
      },
      {
        "id": "progress",
        "type": "n",
        "name": "方案进度"
      },
      {
        "id": "progress_rate",
        "type": "n",
        "name": "方案进度百分比"
      },
      {
        "id": "task_input_power",
        "type": "u",
        "name": "方案总计投入力量"
      },
      {
        "id": "task_input_power_arranged",
        "type": "u",
        "name": "方案当前投入力量"
      }
    ]
  },
  {
    "id": "exit",
    "name": "出口",
    "deprecated": false,
    "attributes": [
      {
        "id": "parent_instance_id",
        "type": "s",
        "name": "出口归属实例ID"
      },
      {
        "id": "type",
        "type": "s",
        "name": "类型"
      },
      {
        "id": "width",
        "type": "n",
        "name": "宽度"
      },
      {
        "id": "height",
        "type": "n",
        "name": "高度"
      },
      {
        "id": "rescue_positions",
        "type": "u",
        "name": "救援力量位置"
      },
      {
        "id": "not_used_positions",
        "type": "u",
        "name": "未部署位置"
      }
    ],
    "bundles": [
      "transform"
    ]
  },
  {
    "id": "barrier_lake",
    "name": "堰塞湖",
    "deprecated": false,
    "attributes": [
      {
        "id": "storage_capacity",
        "type": "s",
        "name": "储水量/库容"
      },
      {
        "id": "barrierlake_area",
        "type": "n",
        "name": "堰塞湖面积"
      },
      {
        "id": "water_depth",
        "type": "s",
        "name": "水深"
      },
      {
        "id": "water_level",
        "type": "s",
        "name": "水位"
      },
      {
        "id": "max_water_level",
        "type": "n",
        "name": "最高水位"
      },
      {
        "id": "water_level_diff",
        "type": "n",
        "name": "上下游水位差"
      },
      {
        "id": "region",
        "type": "n[]",
        "name": "堰塞湖区域"
      },
      {
        "id": "barrier_lake_water_depth",
        "type": "n",
        "name": "堰塞湖底高程"
      },
      {
        "id": "risk_level",
        "type": "n",
        "name": "风险等级"
      },
      {
        "id": "discharging_capacity",
        "type": "n",
        "name": "泄流量"
      },
      {
        "id": "flood_discharge_time",
        "type": "n",
        "name": "泄洪预估所需时长"
      },
      {
        "id": "barrier_lake_safe_water_level",
        "type": "n",
        "name": "堰塞湖安全水位"
      },
      {
        "id": "peak_discharge",
        "type": "n",
        "name": "洪峰流量"
      },
      {
        "id": "flood_peak_time",
        "type": "n",
        "name": "洪峰时间"
      },
      {
        "id": "downstream_runoff_range",
        "type": "n",
        "name": "下游径流范围"
      },
      {
        "id": "warn_range_time",
        "type": "n",
        "name": "到达下游居住区警戒范围的时间"
      },
      {
        "id": "inflow",
        "type": "n",
        "name": "进水流量"
      },
      {
        "id": "outflow",
        "type": "n",
        "name": "出水流量"
      }
    ]
  },
  {
    "id": "mountain_range",
    "name": "山体",
    "deprecated": false,
    "attributes": [
      {
        "id": "slope",
        "type": "n",
        "name": "坡度"
      },
      {
        "id": "slope_direction",
        "type": "n",
        "name": "坡向"
      },
      {
        "id": "height",
        "type": "n",
        "name": "高度"
      },
      {
        "id": "rock_and_soil_density",
        "type": "n",
        "name": "岩土密度"
      },
      {
        "id": "soil_moisture_content",
        "type": "n",
        "name": "岩土含水率"
      },
      {
        "id": "displacement",
        "type": "n",
        "name": "位移量"
      },
      {
        "id": "safety_factor_picture",
        "type": "s",
        "name": "边坡稳定性图片"
      },
      {
        "id": "safety_factor_tif_url",
        "type": "s",
        "name": "边坡稳定性tif"
      },
      {
        "id": "safety_factor_data",
        "type": "u",
        "name": "边坡稳定性数据"
      },
      {
        "id": "landslide_flag",
        "type": "s",
        "name": "是否已发生滑坡"
      },
      {
        "id": "landslide_probability",
        "type": "n",
        "name": "滑坡发生概率"
      },
      {
        "id": "landslide_time",
        "type": "n",
        "name": "滑坡发生时间"
      },
      {
        "id": "landslide_volume",
        "type": "n",
        "name": "滑坡量"
      },
      {
        "id": "safety_factor",
        "type": "n",
        "name": "安全系数"
      },
      {
        "id": "landslide_sliding_height",
        "type": "n",
        "name": "滑坡滑动高度"
      },
      {
        "id": "landslide_pile_up_weir_body",
        "type": "n",
        "name": "滑坡堆积到堰塞体上的方量"
      },
      {
        "id": "landslide_pile_up_barrier_lake",
        "type": "n",
        "name": "滑坡堆积到堰塞湖中的方量"
      },
      {
        "id": "landslide_pile_up_position",
        "type": "n",
        "name": "滑坡堆积位置"
      },
      {
        "id": "landslide_pile_up_area",
        "type": "n",
        "name": "滑坡堆积范围"
      },
      {
        "id": "debris_flow_probability",
        "type": "n",
        "name": "泥石流发生概率"
      },
      {
        "id": "string_result",
        "type": "s",
        "name": "文字描述"
      },
      {
        "id": "debris_flow_time",
        "type": "n",
        "name": "泥石流发生时间"
      },
      {
        "id": "debris_flow_number",
        "type": "n",
        "name": "泥石流量"
      },
      {
        "id": "debris_flow_height",
        "type": "n",
        "name": "泥石流滑动高度"
      },
      {
        "id": "debris_flow_pile_up_weir_body",
        "type": "n",
        "name": "泥石流堆积到堰塞体上的方量"
      },
      {
        "id": "debris_flow_pile_up_barrier_lake",
        "type": "n",
        "name": "泥石流堆积到堰塞湖中的方量"
      },
      {
        "id": "debris_flow_pile_up_position",
        "type": "n",
        "name": "泥石流堆积位置"
      },
      {
        "id": "debris_flow_pile_up_area",
        "type": "n",
        "name": "泥石流堆积范围"
      }
    ]
  },
  {
    "id": "dike_node",
    "name": "堤坝节点",
    "deprecated": false,
    "attributes": [
      {
        "id": "elevation",
        "type": "n",
        "name": "高程"
      },
      {
        "id": "height",
        "type": "n",
        "name": "高度"
      },
      {
        "id": "width",
        "type": "n",
        "name": "宽度"
      },
      {
        "id": "shape",
        "type": "s",
        "name": "形状"
      },
      {
        "id": "left_lanes",
        "type": "n",
        "name": "左侧车道"
      },
      {
        "id": "right_lanes",
        "type": "n",
        "name": "由侧车道"
      },
      {
        "id": "grade",
        "type": "s",
        "name": "等级"
      },
      {
        "id": "area",
        "type": "n",
        "name": "面积"
      },
      {
        "id": "type",
        "type": "s",
        "name": "类型"
      },
      {
        "id": "section",
        "type": "s",
        "name": "部分"
      },
      {
        "id": "fortify_flag",
        "type": "n",
        "name": "是否进行加固"
      },
      {
        "id": "stability",
        "type": "n",
        "name": "稳定性"
      },
      {
        "id": "adjacent_nodes",
        "type": "(node:s,control:n)[3][]",
        "name": "邻接及控制点集合"
      },
      {
        "id": "transform/position"
      }
    ],
    "bundles": [
      "container"
    ]
  },
  {
    "id": "landmark",
    "name": "地标",
    "deprecated": false,
    "attributes": [
      {
        "id": "transform/position"
      },
      {
        "id": "tags",
        "type": "s[]",
        "name": "标签"
      }
    ]
  },
  {
    "id": "wait_transferred_area",
    "name": "待转区",
    "deprecated": false,
    "attributes": [
      {
        "id": "name",
        "type": "s",
        "name": "名称"
      },
      {
        "id": "位置",
        "type": "n",
        "name": "transform/position"
      },
      {
        "id": "people_num",
        "type": "n",
        "name": "人数"
      }
    ],
    "bundles": [
      "wait_transferred_area"
    ]
  },
  {
    "id": "buried_point",
    "name": "压埋点",
    "deprecated": false,
    "attributes": [
      {
        "id": "name",
        "type": "s",
        "name": "名称"
      },
      {
        "id": "depth",
        "type": "n",
        "name": "深度"
      },
      {
        "id": "time",
        "type": "n",
        "name": "时间(h)"
      },
      {
        "id": "people_num",
        "type": "n",
        "name": "人数"
      },
      {
        "id": "alive_people_num",
        "type": "n",
        "name": "存活人数"
      },
      {
        "id": "injury_degree",
        "type": "u",
        "name": "受伤程度"
      },
      {
        "id": "need_volume",
        "type": "n",
        "name": "需要挖掘方量"
      },
      {
        "id": "excavated_volume",
        "type": "n",
        "name": "已挖方量"
      },
      {
        "id": "region",
        "type": "n[]",
        "name": "压埋区域"
      },
      {
        "id": "buried_area",
        "type": "n",
        "name": "压埋面积"
      },
      {
        "id": "state",
        "type": "n",
        "name": "状态"
      },
      {
        "id": "choose_state",
        "type": "n",
        "name": "选择状态"
      }
    ],
    "bundles": [
      "transform"
    ]
  },
  {
    "id": "earthquake",
    "name": "地震",
    "deprecated": false,
    "attributes": [
      {
        "id": "transform/position"
      },
      {
        "id": "transform/coordinates"
      },
      {
        "id": "type",
        "type": "s",
        "name": "地震类型"
      },
      {
        "id": "seismic_wave_type",
        "type": "s",
        "name": "地震波类型"
      },
      {
        "id": "earthquake_level",
        "type": "n",
        "name": "震级"
      },
      {
        "id": "earthquake_time",
        "type": "s",
        "name": "发震时间"
      },
      {
        "id": "earthquake_depth",
        "type": "n",
        "name": "震源深度"
      },
      {
        "id": "rescue_route",
        "type": "u",
        "name": "救援路线"
      },
      {
        "id": "rescue_priority",
        "type": "u",
        "name": "救援优先级"
      }
    ]
  },
  {
    "id": "$instance_factory",
    "name": "实例工厂",
    "deprecated": false,
    "attributes": [
      {
        "id": "$instances",
        "type": "u"
      }
    ]
  },
  {
    "id": "dangerous_rock_mass",
    "name": "危岩体",
    "deprecated": false,
    "attributes": [
      {
        "id": "transform/position"
      },
      {
        "id": "name",
        "type": "s",
        "name": "名称"
      },
      {
        "id": "type",
        "type": "s",
        "name": "类型"
      },
      {
        "id": "landslide_amount_sumtotal",
        "type": "n",
        "name": "滑坡量"
      },
      {
        "id": "landslide_amount",
        "type": "n",
        "name": "危岩体量"
      },
      {
        "id": "excavated_volume",
        "type": "n",
        "name": "已挖方量"
      },
      {
        "id": "landslide_height",
        "type": "n",
        "name": "滑坡体/边坡高度"
      },
      {
        "id": "landslide_up_width",
        "type": "n",
        "name": "滑坡体/边坡上宽"
      },
      {
        "id": "landslide_down_width",
        "type": "n",
        "name": "滑坡体/边坡底宽"
      },
      {
        "id": "landslide_incline_length",
        "type": "n",
        "name": "滑坡体/边坡斜面长"
      },
      {
        "id": "region",
        "type": "n[]",
        "name": "滑坡区域"
      },
      {
        "id": "landslide_area",
        "type": "n",
        "name": "滑坡区域面积"
      },
      {
        "id": "work_space_num",
        "type": "n",
        "name": "作业数量"
      },
      {
        "id": "work_space",
        "type": "u",
        "name": "作业空间"
      },
      {
        "id": "drm_clearn",
        "type": "b",
        "name": "是否清除危岩体"
      },
      {
        "id": "state",
        "type": "n",
        "name": "状态"
      },
      {
        "id": "choose_state",
        "type": "n",
        "name": "选择状态"
      }
    ],
    "bundles": [
      "transform"
    ]
  },
  {
    "id": "rain",
    "name": "雨",
    "deprecated": false,
    "attributes": [
      {
        "id": "type",
        "type": "s",
        "name": "环境类型"
      },
      {
        "id": "temperature",
        "type": "n",
        "name": "温度"
      },
      {
        "id": "wind_intensity",
        "type": "n",
        "name": "风力强度"
      },
      {
        "id": "snowfall",
        "type": "n",
        "name": "降雪量"
      },
      {
        "id": "snowfall_time",
        "type": "n",
        "name": "降雪时长"
      },
      {
        "id": "rainfall",
        "type": "n",
        "name": "降雨量"
      },
      {
        "id": "rainfall_time",
        "type": "n",
        "name": "降雨时长"
      },
      {
        "id": "work_efficiency",
        "type": "n",
        "name": "增效/降效系数"
      },
      {
        "id": "rainfall_intensity",
        "type": "n",
        "name": "降雨强度"
      },
      {
        "id": "rainfall_duration",
        "type": "u",
        "name": "降雨历时"
      },
      {
        "id": "influx_traffic",
        "type": "n",
        "name": "涌入流量"
      },
      {
        "id": "impact",
        "type": "n",
        "name": "影响范围"
      }
    ]
  },
  {
    "id": "rescue_personnel",
    "name": "抢险人员",
    "deprecated": false,
    "attributes": [
      {
        "id": "task_id",
        "type": "s",
        "name": "任务id"
      },
      {
        "id": "blasting_construction_speed",
        "type": "n",
        "name": "爆破施工速度"
      },
      {
        "id": "reinforcement construction_speed",
        "type": "n",
        "name": "加固施工速度"
      },
      {
        "id": "personnel_search_efficiency",
        "type": "n",
        "name": "人员搜救效率"
      }
    ],
    "bundles": [
      "mobile",
      "transform",
      "controlled"
    ]
  },
  {
    "id": "transmission_line",
    "name": "输电线",
    "deprecated": false,
    "attributes": [
      {
        "id": "endpoints",
        "type": "(node:s,point:s)[2]",
        "name": "端点"
      },
      {
        "id": "type",
        "type": "s",
        "name": "类型"
      },
      {
        "id": "material",
        "type": "s",
        "name": "材质"
      },
      {
        "id": "sectional_area",
        "type": "n",
        "name": "截面积"
      },
      {
        "id": "voltage_level",
        "type": "s",
        "name": "电压等级"
      },
      {
        "id": "damaged",
        "type": "b",
        "name": "是否损坏"
      },
      {
        "id": "horizontal_span",
        "type": "n",
        "name": "水平档距"
      },
      {
        "id": "vertical_span",
        "type": "n",
        "name": "垂直档距"
      }
    ]
  },
  {
    "id": "tropical_cyclone",
    "name": "热带气旋",
    "deprecated": false,
    "attributes": [
      {
        "id": "transform/position"
      },
      {
        "id": "level",
        "type": "n",
        "name": "气旋等级"
      },
      {
        "id": "type",
        "type": "s",
        "name": "气旋类型"
      },
      {
        "id": "wind_power",
        "type": "n",
        "name": "风力"
      },
      {
        "id": "wind_level",
        "type": "n",
        "name": "风级"
      },
      {
        "id": "wind_radius",
        "type": "(level:n,radius:n[2])[]",
        "name": "风圈"
      }
    ]
  },
  {
    "id": "downstream_residential_area",
    "name": "下游居住区",
    "deprecated": false,
    "attributes": [
      {
        "id": "transform/position",
        "type": "n",
        "name": "位置"
      },
      {
        "id": "region",
        "type": "n[]",
        "name": "下游区域"
      },
      {
        "id": "submerge_area",
        "type": "n",
        "name": "淹没面积"
      },
      {
        "id": "downstream_depth",
        "type": "n",
        "name": "下游水位"
      },
      {
        "id": "people_num",
        "type": "n",
        "name": "人员数量"
      },
      {
        "id": "distance_from_barrier_lake",
        "type": "n",
        "name": "距离堰塞湖距离"
      },
      {
        "id": "alert_distance",
        "type": "n",
        "name": "警戒距离"
      },
      {
        "id": "warning_water_level",
        "type": "n",
        "name": "警戒水位"
      },
      {
        "id": "alert_peak_flow_rate",
        "type": "n",
        "name": "警戒洪峰流量"
      }
    ]
  },
  {
    "id": "underground_parking",
    "name": "地下停车场",
    "deprecated": false,
    "attributes": [
      {
        "id": "region",
        "type": "n[][]",
        "name": "地下停车场区域"
      },
      {
        "id": "underground_area",
        "type": "n",
        "name": "地下停车场区域"
      },
      {
        "id": "underground_parking_length",
        "type": "n",
        "name": "地下停车场长度"
      },
      {
        "id": "underground_parking_width",
        "type": "n",
        "name": "地下停车场宽度"
      },
      {
        "id": "underground_parking_height",
        "type": "n",
        "name": "地下停车场高度"
      },
      {
        "id": "entrance_exit_num",
        "type": "n",
        "name": "出入口数量"
      },
      {
        "id": "entrance_exit_width",
        "type": "n",
        "name": "出入口宽度"
      },
      {
        "id": "flooding_depth",
        "type": "n",
        "name": "淹没水深"
      },
      {
        "id": "max_flooding_depth",
        "type": "n",
        "name": "最大淹没水深"
      },
      {
        "id": "flooding_water_volume",
        "type": "n",
        "name": "淹没水量"
      },
      {
        "id": "max_flooding_water_volume",
        "type": "n",
        "name": "最大淹没水量"
      },
      {
        "id": "work_space_num",
        "type": "n",
        "name": "作业数量"
      },
      {
        "id": "work_space",
        "type": "u",
        "name": "作业空间"
      }
    ]
  },
  {
    "id": "transmission_tower",
    "name": "输电塔",
    "deprecated": false,
    "attributes": [
      {
        "id": "transform/position"
      },
      {
        "id": "height",
        "type": "n",
        "name": "高度"
      },
      {
        "id": "type",
        "type": "s",
        "name": "类型"
      },
      {
        "id": "material",
        "type": "s",
        "name": "材质"
      },
      {
        "id": "damaged",
        "type": "s",
        "name": "是否损坏"
      },
      {
        "id": "tower_damage_type",
        "type": "s",
        "name": "输电塔损坏类型"
      },
      {
        "id": "damageType",
        "type": "n[]",
        "name": "损坏类型"
      },
      {
        "id": "Point",
        "type": "n[3][][]",
        "name": "点集"
      }
    ]
  },
  {
    "id": "team",
    "name": "队伍",
    "deprecated": false,
    "attributes": [
      {
        "id": "team_name",
        "type": "s",
        "name": "队伍名称"
      },
      {
        "id": "march_type",
        "type": "s",
        "name": "行进方式"
      },
      {
        "id": "march_distance",
        "type": "n",
        "name": "行进距离"
      },
      {
        "id": "march_time",
        "type": "n",
        "name": "行进时间"
      },
      {
        "id": "people_num",
        "type": "n",
        "name": "队伍人数"
      },
      {
        "id": "equipment_info",
        "type": "u",
        "name": "装备信息"
      },
      {
        "id": "remaining_march_time",
        "type": "n",
        "name": "剩余行进时间"
      }
    ],
    "bundles": [
      "mobile",
      "transform",
      "controlled"
    ]
  },
  {
    "id": "blockage",
    "name": "壅塞体",
    "deprecated": false,
    "attributes": [
      {
        "id": "transform/position"
      },
      {
        "id": "volume",
        "type": "n",
        "name": "泥石流量"
      },
      {
        "id": "type",
        "type": "s",
        "name": "流域形态"
      },
      {
        "id": "state",
        "type": "s",
        "name": "物质状态"
      }
    ]
  },
  {
    "id": "settlement",
    "name": "安置点",
    "deprecated": false,
    "attributes": [
      {
        "id": "transform/position"
      },
      {
        "id": "people_num",
        "type": "n",
        "name": "人员数量"
      },
      {
        "id": "name",
        "type": "s",
        "name": "名称"
      },
      {
        "id": "structure_type",
        "type": "s",
        "name": "结构类型"
      }
    ]
  },
  {
    "id": "boulder",
    "name": "巨石",
    "deprecated": false,
    "attributes": [
      {
        "id": "type",
        "type": "n",
        "name": "类型"
      },
      {
        "id": "length",
        "type": "n",
        "name": "长"
      },
      {
        "id": "width",
        "type": "n",
        "name": "宽"
      },
      {
        "id": "height",
        "type": "n",
        "name": "高"
      },
      {
        "id": "volume",
        "type": "n",
        "name": "体积"
      },
      {
        "id": "state",
        "type": "n",
        "name": "状态"
      },
      {
        "id": "choose_state",
        "type": "n",
        "name": "选择状态"
      }
    ],
    "bundles": [
      "transform"
    ]
  },
  {
    "id": "road",
    "name": "道路节点",
    "deprecated": false,
    "attributes": [
      {
        "id": "transform/position"
      },
      {
        "id": "width",
        "type": "n",
        "name": "宽度"
      },
      {
        "id": "road_index",
        "type": "n",
        "name": "节点序号"
      },
      {
        "id": "elevation",
        "type": "n",
        "name": "高程"
      },
      {
        "id": "neighbors",
        "type": "(node:s,control:n[3][2])[]",
        "name": "邻接点集"
      },
      {
        "id": "material",
        "type": "s",
        "name": "材质"
      },
      {
        "id": "section",
        "type": "s[]",
        "name": "路段"
      },
      {
        "id": "damage_type",
        "type": "s",
        "name": "损坏类型"
      },
      {
        "id": "damage_height",
        "type": "n",
        "name": "损坏高度"
      },
      {
        "id": "damage_width",
        "type": "n",
        "name": "损坏宽度"
      },
      {
        "id": "damage_length",
        "type": "n",
        "name": "损坏长度"
      },
      {
        "id": "way_name",
        "type": "s",
        "name": "道路名称"
      },
      {
        "id": "way_length",
        "type": "n",
        "name": "道路长度"
      },
      {
        "id": "damage_name",
        "type": "s",
        "name": "损毁段名称"
      },
      {
        "id": "state",
        "type": "n",
        "name": "状态"
      },
      {
        "id": "choose_state",
        "type": "n",
        "name": "选择状态"
      },
      {
        "id": "work_space_num",
        "type": "n",
        "name": "作业数量"
      },
      {
        "id": "work_space",
        "type": "u",
        "name": "作业空间"
      }
    ]
  },
  {
    "id": "residential_area",
    "name": "居住区",
    "deprecated": false,
    "attributes": [
      {
        "id": "transform/position"
      },
      {
        "id": "type",
        "type": "s",
        "name": "类型"
      },
      {
        "id": "people_num",
        "type": "n",
        "name": "人员数量"
      },
      {
        "id": "affected_area",
        "type": "n",
        "name": "受灾面积"
      },
      {
        "id": "structure_type",
        "type": "s",
        "name": "结构类型"
      },
      {
        "id": "name",
        "type": "s",
        "name": "名称"
      },
      {
        "id": "flooding_depth",
        "type": "n",
        "name": "积水水深"
      }
    ]
  },
  {
    "id": "board",
    "name": "公告板",
    "deprecated": false,
    "attributes": [
      {
        "id": "transform/position"
      },
      {
        "id": "location",
        "type": "n",
        "name": "地点"
      },
      {
        "id": "lonlat",
        "type": "s",
        "name": "经纬度"
      },
      {
        "id": "affected_area",
        "type": "s",
        "name": "受灾面积"
      },
      {
        "id": "road_len",
        "type": "s",
        "name": "道路长度"
      },
      {
        "id": "road_width",
        "type": "s",
        "name": "道路宽度"
      },
      {
        "id": "road_material",
        "type": "s",
        "name": "道路材质"
      },
      {
        "id": "affected_type",
        "type": "s",
        "name": "损坏类型"
      },
      {
        "id": "affected_len",
        "type": "s",
        "name": "损坏长度"
      },
      {
        "id": "affected_width",
        "type": "s",
        "name": "损坏宽度"
      },
      {
        "id": "river_len",
        "type": "s",
        "name": "河道长度"
      },
      {
        "id": "river_width",
        "type": "s",
        "name": "河道宽度"
      },
      {
        "id": "river_height",
        "type": "s",
        "name": "平均高度"
      },
      {
        "id": "blocking_type",
        "type": "s",
        "name": "堵塞类型"
      },
      {
        "id": "blocking_len",
        "type": "s",
        "name": "堵塞长度"
      },
      {
        "id": "blocking_width",
        "type": "s",
        "name": "堵塞宽度"
      },
      {
        "id": "area_shap",
        "type": "s",
        "name": "流域形态"
      },
      {
        "id": "material_shap",
        "type": "s",
        "name": "物质状态"
      },
      {
        "id": "flow_rate",
        "type": "s",
        "name": "泥石流量"
      }
    ]
  },
  {
    "id": "river_node",
    "name": "河流节点",
    "deprecated": false,
    "attributes": [
      {
        "id": "transform/position"
      },
      {
        "id": "river_node_index",
        "type": "n",
        "name": "节点序号"
      },
      {
        "id": "width",
        "type": "n",
        "name": "宽度"
      },
      {
        "id": "depth",
        "type": "n",
        "name": "深度"
      },
      {
        "id": "elevation",
        "type": "n",
        "name": "高程"
      },
      {
        "id": "neighbors",
        "type": "(node:s,control:n[3][2])[]",
        "name": "邻接点集"
      },
      {
        "id": "upstream_water_level",
        "type": "n",
        "name": "上游水位"
      },
      {
        "id": "downstream_water_level",
        "type": "n",
        "name": "下游水位"
      },
      {
        "id": "downstream_velocity",
        "type": "n",
        "name": "预测最大流速"
      },
      {
        "id": "downstream_flow_rate",
        "type": "n",
        "name": "预测最大流量"
      },
      {
        "id": "upstream_inflow",
        "type": "n",
        "name": "上游来水量"
      },
      {
        "id": "total_inflow",
        "type": "n",
        "name": "入库水量"
      },
      {
        "id": "avg_velocity_flow",
        "type": "n",
        "name": "平均流速"
      },
      {
        "id": "upstream_catchment_area",
        "type": "n",
        "name": "上游集雨面积"
      },
      {
        "id": "sum_input_water",
        "type": "n",
        "name": "汇总入水量"
      },
      {
        "id": "region",
        "type": "n[]",
        "name": "河流区域"
      },
      {
        "id": "inputs",
        "type": "(node:s,control:n[3],velocity:n)[]",
        "name": "输入"
      },
      {
        "id": "outputs",
        "type": "(node:s,control:n[3],velocity:n)[]",
        "name": "输出"
      },
      {
        "id": "section",
        "type": "s",
        "name": "河段"
      },
      {
        "id": "blockage_type",
        "type": "s",
        "name": "堵塞类型"
      },
      {
        "id": "blockage_width",
        "type": "n",
        "name": "堵塞宽度"
      },
      {
        "id": "blockage_length",
        "type": "n",
        "name": "堵塞长度"
      },
      {
        "id": "work_space_num",
        "type": "n",
        "name": "作业数量"
      },
      {
        "id": "work_space",
        "type": "u",
        "name": "作业空间"
      }
    ]
  },
  {
    "id": "task",
    "name": "救援任务",
    "deprecated": false,
    "attributes": [
      {
        "id": "transform/position"
      },
      {
        "id": "controlled/status"
      },
      {
        "id": "type",
        "type": "s",
        "name": "任务类型"
      },
      {
        "id": "upstream",
        "type": "s[]",
        "name": "上游任务"
      },
      {
        "id": "downstream",
        "type": "s[]",
        "name": "下游任务"
      },
      {
        "id": "children",
        "type": "s[]",
        "name": "子任务"
      },
      {
        "id": "parent",
        "type": "s",
        "name": "父任务"
      },
      {
        "id": "plan",
        "type": "s",
        "name": "救援方案"
      },
      {
        "id": "trigger",
        "type": "u",
        "name": "触发器"
      },
      {
        "id": "amount",
        "type": "n",
        "name": "任务总量"
      },
      {
        "id": "task_info",
        "type": "u",
        "name": "任务内容"
      },
      {
        "id": "progress",
        "type": "n",
        "name": "任务进度"
      },
      {
        "id": "progress_rate",
        "type": "n",
        "name": "任务进度百分比"
      },
      {
        "id": "task_scheme",
        "type": "u",
        "name": "任务推荐方案"
      },
      {
        "id": "task_input_power",
        "type": "u",
        "name": "任务投入力量"
      },
      {
        "id": "task_finish_info",
        "type": "u",
        "name": "任务已完成内容"
      },
      {
        "id": "task_input_power_arranged",
        "type": "u",
        "name": "任务已投入力量"
      },
      {
        "id": "task_parameters",
        "type": "u",
        "name": "任务参数"
      },
      {
        "id": "position_type",
        "type": "n",
        "name": "位置类型"
      },
      {
        "id": "elapsed_time",
        "type": "n",
        "name": "已用时长"
      },
      {
        "id": "estimated_need_time",
        "type": "n",
        "name": "预计还需时长"
      },
      {
        "id": "total_time",
        "type": "n",
        "name": "总用时"
      },
      {
        "id": "pumped_water_volume",
        "type": "n",
        "name": "已抽排水量"
      }
    ]
  },
  {
    "id": "dike",
    "name": "堤坝节点",
    "deprecated": false,
    "attributes": [
      {
        "id": "elevation",
        "type": "n",
        "name": "高程"
      },
      {
        "id": "height",
        "type": "n",
        "name": "高度"
      },
      {
        "id": "width",
        "type": "n",
        "name": "顶宽"
      },
      {
        "id": "bottom_width",
        "type": "n",
        "name": "底宽"
      },
      {
        "id": "slope_ratio",
        "type": "n",
        "name": "坡比"
      },
      {
        "id": "back_slope_ratio",
        "type": "n",
        "name": "背水面坡比"
      },
      {
        "id": "material",
        "type": "s",
        "name": "材质"
      },
      {
        "id": "shape",
        "type": "s",
        "name": "形状"
      },
      {
        "id": "left_lanes",
        "type": "n",
        "name": "左侧车道"
      },
      {
        "id": "right_lanes",
        "type": "n",
        "name": "右侧车道"
      },
      {
        "id": "grade",
        "type": "s",
        "name": "等级"
      },
      {
        "id": "area",
        "type": "n",
        "name": "面积"
      },
      {
        "id": "type",
        "type": "s",
        "name": "类型"
      },
      {
        "id": "section",
        "type": "s",
        "name": "部分"
      },
      {
        "id": "fortify_flag",
        "type": "n",
        "name": "是否进行加固"
      },
      {
        "id": "stability",
        "type": "n",
        "name": "稳定性"
      },
      {
        "id": "neighbors",
        "type": "(node:s,control:n[3][2])[]",
        "name": "邻接点集"
      },
      {
        "id": "transform/position"
      }
    ],
    "bundles": [
      "container"
    ]
  },
  {
    "id": "weir_body",
    "name": "堰塞体",
    "deprecated": false,
    "attributes": [
      {
        "id": "transform/position"
      },
      {
        "id": "region",
        "type": "n[]",
        "name": "堰塞体区域"
      },
      {
        "id": "length",
        "type": "n",
        "name": "长度"
      },
      {
        "id": "width",
        "type": "n",
        "name": "宽度"
      },
      {
        "id": "height",
        "type": "n",
        "name": "高度"
      },
      {
        "id": "lowest_height",
        "type": "n",
        "name": "最低点高度"
      },
      {
        "id": "tallest_height",
        "type": "n",
        "name": "最高点高度"
      },
      {
        "id": "elevation",
        "type": "n",
        "name": "高程"
      },
      {
        "id": "volume",
        "type": "n",
        "name": "体积"
      },
      {
        "id": "avg_area",
        "type": "n",
        "name": "平均面积"
      },
      {
        "id": "cross_section",
        "type": "s",
        "name": "横截面"
      },
      {
        "id": "composition",
        "type": "s",
        "name": "组成物质"
      },
      {
        "id": "permeability_coefficient",
        "type": "n",
        "name": "渗透系数"
      },
      {
        "id": "scouring_coefficient",
        "type": "n",
        "name": "冲刷系数"
      },
      {
        "id": "groove_length",
        "type": "n",
        "name": "挖槽长度"
      },
      {
        "id": "groove_width",
        "type": "n",
        "name": "挖槽宽度"
      },
      {
        "id": "excavated_length",
        "type": "n",
        "name": "已挖长度"
      },
      {
        "id": "excavated_depth",
        "type": "n",
        "name": "已挖深度"
      },
      {
        "id": "need_total_volume",
        "type": "n",
        "name": "需挖总方量"
      },
      {
        "id": "excavated_volume",
        "type": "n",
        "name": "已挖方量"
      },
      {
        "id": "stones_distance",
        "type": "n[]",
        "name": "每块石头距开始间距"
      },
      {
        "id": "stones_points",
        "type": "n[]",
        "name": "每块石头经纬度集合"
      },
      {
        "id": "stone_flag",
        "type": "s",
        "name": "是否出现石头"
      },
      {
        "id": "trenching_countdown",
        "type": "n",
        "name": "挖槽完毕倒计时"
      },
      {
        "id": "temp_trenching_countdown",
        "type": "n",
        "name": "挖槽完毕倒计时"
      },
      {
        "id": "flush_spread_flag",
        "type": "s",
        "name": "是否请求冲刷漫延模型数据"
      },
      {
        "id": "tif_png_srcs",
        "type": "u",
        "name": "冲刷tif和漫延png路径"
      },
      {
        "id": "temp_scour_data",
        "type": "u",
        "name": "临时冲刷数据"
      },
      {
        "id": "scour_data",
        "type": "u",
        "name": "冲刷数据"
      },
      {
        "id": "spread_data",
        "type": "u",
        "name": "漫延数据"
      },
      {
        "id": "tif_png_time",
        "type": "n",
        "name": "冲刷tif和漫延png时刻"
      },
      {
        "id": "tif_png_flag",
        "type": "s",
        "name": "是否请求tif和png数据"
      },
      {
        "id": "ncwl_damoverflow",
        "type": "n",
        "name": "漫坝临界水位（不挖槽）"
      },
      {
        "id": "nct_damoverflow",
        "type": "n",
        "name": "漫坝临界时间（不挖槽）"
      },
      {
        "id": "cwl_damoverflow",
        "type": "n",
        "name": "漫坝临界水位（挖槽）"
      },
      {
        "id": "ct_damoverflow",
        "type": "n",
        "name": "漫坝临界时间（挖槽）"
      },
      {
        "id": "ncwl_dambreak",
        "type": "n",
        "name": "溃坝临界水位（不挖槽）"
      },
      {
        "id": "nct_dambreak",
        "type": "n",
        "name": "溃坝临界时间（不挖槽）"
      },
      {
        "id": "cwl_dambreak",
        "type": "n",
        "name": "溃坝临界水位（挖槽）"
      },
      {
        "id": "ct_dambreak",
        "type": "n",
        "name": "溃坝临界时间（挖槽）"
      },
      {
        "id": "dambody_safetyfactor",
        "type": "n",
        "name": "坝体安全系数"
      },
      {
        "id": "n_dambreak_weirbody_threshold",
        "type": "n",
        "name": "到达溃坝临界状态时堰塞体安全系数阈值（不挖槽）"
      },
      {
        "id": "dambreak_weirbody_threshold",
        "type": "n",
        "name": "到达溃坝临界状态时堰塞体安全系数阈值（挖槽）"
      },
      {
        "id": "start_breach_width",
        "type": "n",
        "name": "初始溃口宽度"
      },
      {
        "id": "breach_width",
        "type": "n",
        "name": "溃口宽度"
      },
      {
        "id": "breach_stable_width",
        "type": "n",
        "name": "溃口稳定宽度"
      }
    ]
  },
  {
    "id": "breach",
    "name": "决口",
    "deprecated": false,
    "attributes": [
      {
        "id": "breach_width",
        "type": "n",
        "name": "宽度"
      },
      {
        "id": "fortify_width",
        "type": "n",
        "name": "加固宽度"
      },
      {
        "id": "seal_width",
        "type": "n",
        "name": "闭气宽度"
      },
      {
        "id": "breach_depth",
        "type": "n",
        "name": "深度"
      },
      {
        "id": "breach_flow_rate",
        "type": "n",
        "name": "流量"
      },
      {
        "id": "breach_angle",
        "type": "n",
        "name": "角度"
      },
      {
        "id": "breach_angle_init",
        "type": "n",
        "name": "初始角度"
      },
      {
        "id": "velocity",
        "type": "n",
        "name": "流速速度"
      },
      {
        "id": "elevation",
        "type": "n",
        "name": "高程"
      },
      {
        "id": "elevation_init",
        "type": "n",
        "name": "初始高程"
      },
      {
        "id": "elevation_top",
        "type": "n",
        "name": "堤坝顶部高程"
      },
      {
        "id": "flood_picture_path",
        "type": "s",
        "name": "淹没图片地址"
      },
      {
        "id": "flood_picture_url",
        "type": "s",
        "name": "淹没图片请求地址"
      },
      {
        "id": "flood_picture",
        "type": "s",
        "name": "淹没图片"
      },
      {
        "id": "dike_ends",
        "type": "(node:s,position:n[3])[2]",
        "name": "堤坝端点"
      },
      {
        "id": "fortify_ends",
        "type": "(node:s,position:n[3])[2]",
        "name": "加固端点"
      },
      {
        "id": "seal_ends",
        "type": "(node:s,position:n[3])[2]",
        "name": "闭气端点"
      },
      {
        "id": "submerge_area",
        "type": "n",
        "name": "淹没面积"
      },
      {
        "id": "downstream_depth",
        "type": "n",
        "name": "下游水位"
      },
      {
        "id": "wrap_head_volume",
        "type": "n",
        "name": "裹头加固物料体积"
      },
      {
        "id": "stability_a",
        "type": "n",
        "name": "左堤裹头加固率"
      },
      {
        "id": "stability_b",
        "type": "n",
        "name": "右堤裹头加固率"
      },
      {
        "id": "stability_a_node",
        "type": "n[3]",
        "name": "左堤裹头加固位置"
      },
      {
        "id": "stability_b_node",
        "type": "n[3]",
        "name": "右堤裹头加固位置"
      },
      {
        "id": "input_material",
        "type": "n",
        "name": "有效投料体积"
      },
      {
        "id": "material_stabilty",
        "type": "n",
        "name": "投料保留率"
      },
      {
        "id": "states",
        "type": "u",
        "name": "状态"
      }
    ],
    "bundles": [
      "transform"
    ]
  },
  {
    "id": "tunnel",
    "name": "隧道",
    "deprecated": false,
    "attributes": [
      {
        "id": "tunnel_length",
        "type": "n",
        "name": "隧道长度"
      },
      {
        "id": "tunnel_width",
        "type": "n",
        "name": "隧道宽度"
      },
      {
        "id": "tunnel_height",
        "type": "n",
        "name": "隧道高度"
      },
      {
        "id": "tunnel_line",
        "type": "n[][]",
        "name": "隧道标线"
      },
      {
        "id": "entrance_exit_num",
        "type": "n",
        "name": "出入口数量"
      },
      {
        "id": "entrance_exit_width",
        "type": "n",
        "name": "出入口宽度"
      },
      {
        "id": "entrance_exit_height",
        "type": "n",
        "name": "出入口高度"
      },
      {
        "id": "flooding_depth",
        "type": "n",
        "name": "淹没水深"
      },
      {
        "id": "max_flooding_depth",
        "type": "n",
        "name": "最大淹没水深"
      },
      {
        "id": "flooding_water_volume",
        "type": "n",
        "name": "淹没水量"
      },
      {
        "id": "max_flooding_water_volume",
        "type": "n",
        "name": "最大淹没水量"
      },
      {
        "id": "work_space_num",
        "type": "n",
        "name": "作业数量"
      },
      {
        "id": "work_space",
        "type": "u",
        "name": "作业空间"
      }
    ]
  },
  {
    "id": "vehicle_yard",
    "name": "载具集结点",
    "deprecated": false,
    "attributes": [
      {
        "id": "tags",
        "type": "s[]",
        "name": "标签"
      },
      {
        "id": "type",
        "type": "s",
        "name": "类型"
      },
      {
        "id": "round_trip_time",
        "type": "n",
        "name": "往返时间"
      },
      {
        "id": "route_distance",
        "type": "n",
        "name": "航线距离"
      },
      {
        "id": "digger_count",
        "type": "n",
        "name": "反铲挖掘机数量"
      },
      {
        "id": "dozer_count",
        "type": "n",
        "name": "推土机数量"
      },
      {
        "id": "dumper_count",
        "type": "n",
        "name": "自卸车数量"
      },
      {
        "id": "water_pump_count",
        "type": "n",
        "name": "水泵数量"
      },
      {
        "id": "siphon_count",
        "type": "n",
        "name": "虹吸管数量"
      },
      {
        "id": "helicopter_count",
        "type": "n",
        "name": "直升机数量"
      },
      {
        "id": "rescue_personnel_count",
        "type": "n",
        "name": "抢险人员数量"
      },
      {
        "id": "transport_count",
        "type": "n",
        "name": "运输车数量"
      },
      {
        "id": "explosive_count",
        "type": "n",
        "name": "炸药量"
      },
      {
        "id": "safe_distance",
        "type": "n",
        "name": "安全距离"
      }
    ],
    "bundles": [
      "transform"
    ]
  }
]